pybengengphonetic/__init__.py
pybengengphonetic/config.py
pybengengphonetic/conparse.py
pybengengphonetic/hinavro.py
pybengengphonetic/resources/avrodict.json
pybengengphonetic/utils/__init__.py
pybengengphonetic/utils/count.py
pybengengphonetic/utils/validate.py
pybengengphonetic-2.0.0.dist-info/LICENSE
pybengengphonetic-2.0.0.dist-info/METADATA
pybengengphonetic-2.0.0.dist-info/WHEEL
pybengengphonetic-2.0.0.dist-info/top_level.txt
pybengengphonetic-2.0.0.dist-info/RECORD
