Metadata-Version: 2.1
Name: pybengengphonetic
Version: 2.0.0
Summary: Python implementation to convert bengali to phonetic
Home-page: https://github.com/SubrataSarkar32/pybengengphonetic
Author: Subrata Sarkar
Author-email: subrotosarkar32@gmail.com
License: GNU GPL v3 or later
Classifier: Development Status :: 3 - Alpha
Classifier: Intended Audience :: Developers
Classifier: License :: OSI Approved :: GNU General Public License v3 or later (GPLv3+)
Classifier: Operating System :: OS Independent
Classifier: Programming Language :: Python :: 3
License-File: LICENSE
Requires-Dist: pyttsx3 >=2.90
